README.md
setup.py
globomap_driver_napi/__init__.py
globomap_driver_napi/data_spec.py
globomap_driver_napi/driver.py
globomap_driver_napi/kind.py
globomap_driver_napi/loader.py
globomap_driver_napi/networkapi.py
globomap_driver_napi/rabbitmq.py
globomap_driver_napi/settings.py
globomap_driver_napi/util.py
globomap_driver_napi.egg-info/PKG-INFO
globomap_driver_napi.egg-info/SOURCES.txt
globomap_driver_napi.egg-info/dependency_links.txt
globomap_driver_napi.egg-info/requires.txt
globomap_driver_napi.egg-info/top_level.txt