Metadata-Version: 1.0
Name: globomap-driver-napi
Version: 0.0.30
Summary: Python library for globomap-driver to get data from GloboNetworkAPI
Home-page: https://github.com/globocom/globomap-driver-napi
Author: Ederson Brilhante
Author-email: ederson.brilhante@corp.globo.com
License: UNKNOWN
Platform: UNKNOWN
